src/encoder.v
module encoder_16_to_4 (
    input  [15:0] in,
    output reg [3:0] out,
    output reg valid
);
    // Using casez and '?' instead of casex to pass strict Verilator linting
    always @(*) begin
        casez (in)
            16'b1???_????_????_????: begin out = 4'd15; valid = 1; end
            16'b01??_????_????_????: begin out = 4'd14; valid = 1; end
            16'b001?_????_????_????: begin out = 4'd13; valid = 1; end
            16'b0001_????_????_????: begin out = 4'd12; valid = 1; end
            16'b0000_1???_????_????: begin out = 4'd11; valid = 1; end
            16'b0000_01??_????_????: begin out = 4'd10; valid = 1; end
            16'b0000_001?_????_????: begin out = 4'd9;  valid = 1; end
            16'b0000_0001_????_????: begin out = 4'd8;  valid = 1; end
            16'b0000_0000_1???_????: begin out = 4'd7;  valid = 1; end
            16'b0000_0000_01??_????: begin out = 4'd6;  valid = 1; end
            16'b0000_0000_001?_????: begin out = 4'd5;  valid = 1; end
            16'b0000_0000_0001_????: begin out = 4'd4;  valid = 1; end
            16'b0000_0000_0000_1???: begin out = 4'd3;  valid = 1; end
            16'b0000_0000_0000_01??: begin out = 4'd2;  valid = 1; end
            16'b0000_0000_0000_001?: begin out = 4'd1;  valid = 1; end
            16'b0000_0000_0000_0001: begin out = 4'd0;  valid = 1; end
            default: begin out = 4'd0; valid = 0; end
        endcase
    end
endmodule

module encoder_256_to_8 (
    input  [255:0] in,
    output [7:0] out,
    output valid
);
    // 64-bit flat bus (16 blocks * 4 bits per block) to avoid 2D array warnings
    wire [63:0] block_out_flat; 
    wire [15:0] block_valid;
    wire [3:0]  block_addr;
    wire [3:0]  offset_addr;

    // 1. Instantiate 16 encoders of 16-bits each
    genvar i;
    generate
        for (i = 0; i < 16; i = i + 1) begin : encoder_blocks
            encoder_16_to_4 u_enc (
                .in(in[(i*16)+15 : i*16]),
                .out(block_out_flat[(i*4)+3 : i*4]), 
                .valid(block_valid[i])
            );
        end
    endgenerate

    // 2. Priority encode the block_valid signals
    encoder_16_to_4 master_enc (
        .in(block_valid),
        .out(block_addr),
        .valid(valid)
    );

    // 3. Select the offset from the active block
    assign offset_addr = block_out_flat[(block_addr * 4) +: 4];

    // 4. Concatenate: [High 4 bits (block index), Low 4 bits (within block)]
    assign out = {block_addr, offset_addr};
endmodule

src/encodertb.v
`timescale 1ns / 1ps

module tb_encoder();
    reg [255:0] in;
    wire [7:0] out;
    wire valid;

    encoder_256_to_8 uut (.in(in), .out(out), .valid(valid));

    integer i;

    initial begin
        $dumpfile("encoder_verification.vcd");
        $dumpvars(0, tb_encoder);

        $display("Starting Automated Verification...");

        // 1. Test All Single Bits
        for (i = 0; i < 256; i = i + 1) begin
            in = 256'b0;
            in[i] = 1'b1;
            #1;
            if (out !== i || valid !== 1'b1) begin
                $display("FAIL: Single bit test failed at bit %d", i);
            end
        end
        $display("Passed: Single bit tests.");

        // 2. Test Priority Logic (Randomized)
        repeat (100) begin
            in = $random; // Note: For 256 bits, use a better RNG if needed
            // Logic to determine expected output
            // (Highest bit index active)
            #1;
            // Add custom checker logic here if needed
        end

        $display("Verification Complete.");
        $finish;
    end
endmodule

src/encoder_verification.vcd
$date
	Thu Jun 25 10:50:50 2026
$end
$version
	Icarus Verilog
$end
$timescale
	1ps
$end
$scope module tb_encoder $end
$var wire 1 ! valid $end
$var wire 8 " out [7:0] $end
$var reg 256 # in [255:0] $end
$var integer 32 $ i [31:0] $end
$scope module uut $end
$var wire 256 % in [255:0] $end
$var wire 1 ! valid $end
$var wire 8 & out [7:0] $end
$var wire 4 ' offset_addr [3:0] $end
$var wire 16 ( block_valid [15:0] $end
$var wire 64 ) block_out_flat [63:0] $end
$var wire 4 * block_addr [3:0] $end
$scope begin encoder_blocks[0] $end
$var parameter 2 + i $end
$scope module u_enc $end
$var wire 16 , in [15:0] $end
$var reg 4 - out [3:0] $end
$var reg 1 . valid $end
$upscope $end
$upscope $end
$scope begin encoder_blocks[1] $end
$var parameter 2 / i $end
$scope module u_enc $end
$var wire 16 0 in [15:0] $end
$var reg 4 1 out [3:0] $end
$var reg 1 2 valid $end
$upscope $end
$upscope $end
$scope begin encoder_blocks[2] $end
$var parameter 3 3 i $end
$scope module u_enc $end
$var wire 16 4 in [15:0] $end
$var reg 4 5 out [3:0] $end
$var reg 1 6 valid $end
$upscope $end
$upscope $end
$scope begin encoder_blocks[3] $end
$var parameter 3 7 i $end
$scope module u_enc $end
$var wire 16 8 in [15:0] $end
$var reg 4 9 out [3:0] $end
$var reg 1 : valid $end
$upscope $end
$upscope $end
$scope begin encoder_blocks[4] $end
$var parameter 4 ; i $end
$scope module u_enc $end
$var wire 16 < in [15:0] $end
$var reg 4 = out [3:0] $end
$var reg 1 > valid $end
$upscope $end
$upscope $end
$scope begin encoder_blocks[5] $end
$var parameter 4 ? i $end
$scope module u_enc $end
$var wire 16 @ in [15:0] $end
$var reg 4 A out [3:0] $end
$var reg 1 B valid $end
$upscope $end
$upscope $end
$scope begin encoder_blocks[6] $end
$var parameter 4 C i $end
$scope module u_enc $end
$var wire 16 D in [15:0] $end
$var reg 4 E out [3:0] $end
$var reg 1 F valid $end
$upscope $end
$upscope $end
$scope begin encoder_blocks[7] $end
$var parameter 4 G i $end
$scope module u_enc $end
$var wire 16 H in [15:0] $end
$var reg 4 I out [3:0] $end
$var reg 1 J valid $end
$upscope $end
$upscope $end
$scope begin encoder_blocks[8] $end
$var parameter 5 K i $end
$scope module u_enc $end
$var wire 16 L in [15:0] $end
$var reg 4 M out [3:0] $end
$var reg 1 N valid $end
$upscope $end
$upscope $end
$scope begin encoder_blocks[9] $end
$var parameter 5 O i $end
$scope module u_enc $end
$var wire 16 P in [15:0] $end
$var reg 4 Q out [3:0] $end
$var reg 1 R valid $end
$upscope $end
$upscope $end
$scope begin encoder_blocks[10] $end
$var parameter 5 S i $end
$scope module u_enc $end
$var wire 16 T in [15:0] $end
$var reg 4 U out [3:0] $end
$var reg 1 V valid $end
$upscope $end
$upscope $end
$scope begin encoder_blocks[11] $end
$var parameter 5 W i $end
$scope module u_enc $end
$var wire 16 X in [15:0] $end
$var reg 4 Y out [3:0] $end
$var reg 1 Z valid $end
$upscope $end
$upscope $end
$scope begin encoder_blocks[12] $end
$var parameter 5 [ i $end
$scope module u_enc $end
$var wire 16 \ in [15:0] $end
$var reg 4 ] out [3:0] $end
$var reg 1 ^ valid $end
$upscope $end
$upscope $end
$scope begin encoder_blocks[13] $end
$var parameter 5 _ i $end
$scope module u_enc $end
$var wire 16 ` in [15:0] $end
$var reg 4 a out [3:0] $end
$var reg 1 b valid $end
$upscope $end
$upscope $end
$scope begin encoder_blocks[14] $end
$var parameter 5 c i $end
$scope module u_enc $end
$var wire 16 d in [15:0] $end
$var reg 4 e out [3:0] $end
$var reg 1 f valid $end
$upscope $end
$upscope $end
$scope begin encoder_blocks[15] $end
$var parameter 5 g i $end
$scope module u_enc $end
$var wire 16 h in [15:0] $end
$var reg 4 i out [3:0] $end
$var reg 1 j valid $end
$upscope $end
$upscope $end
$scope module master_enc $end
$var wire 16 k in [15:0] $end
$var reg 4 l out [3:0] $end
$var reg 1 ! valid $end
$upscope $end
$upscope $end
$upscope $end
$enddefinitions $end
$comment Show the parameter values. $end
$dumpall
b1111 g
b1110 c
b1101 _
b1100 [
b1011 W
b1010 S
b1001 O
b1000 K
b111 G
b110 C
b101 ?
b100 ;
b11 7
b10 3
b1 /
b0 +
$end
#0
$dumpvars
b0 l
b1 k
0j
b0 i
b0 h
0f
b0 e
b0 d
0b
b0 a
b0 `
0^
b0 ]
b0 \
0Z
b0 Y
b0 X
0V
b0 U
b0 T
0R
b0 Q
b0 P
0N
b0 M
b0 L
0J
b0 I
b0 H
0F
b0 E
b0 D
0B
b0 A
b0 @
0>
b0 =
b0 <
0:
b0 9
b0 8
06
b0 5
b0 4
02
b0 1
b0 0
1.
b0 -
b1 ,
b0 *
b0 )
b1 (
b0 '
b0 &
b1 %
b0 $
b1 #
b0 "
1!
$end
#1000
b1 "
b1 &
b1 '
b1 )
b1 -
b10 ,
b10 #
b10 %
b1 $
#2000
b10 "
b10 &
b10 '
b10 )
b10 -
b100 ,
b100 #
b100 %
b10 $
#3000
b11 "
b11 &
b11 '
b11 )
b11 -
b1000 ,
b1000 #
b1000 %
b11 $
#4000
b100 "
b100 &
b100 '
b100 )
b100 -
b10000 ,
b10000 #
b10000 %
b100 $
#5000
b101 "
b101 &
b101 '
b101 )
b101 -
b100000 ,
b100000 #
b100000 %
b101 $
#6000
b110 "
b110 &
b110 '
b110 )
b110 -
b1000000 ,
b1000000 #
b1000000 %
b110 $
#7000
b111 "
b111 &
b111 '
b111 )
b111 -
b10000000 ,
b10000000 #
b10000000 %
b111 $
#8000
b1000 "
b1000 &
b1000 '
b1000 )
b1000 -
b100000000 ,
b100000000 #
b100000000 %
b1000 $
#9000
b1001 "
b1001 &
b1001 '
b1001 )
b1001 -
b1000000000 ,
b1000000000 #
b1000000000 %
b1001 $
#10000
b1010 "
b1010 &
b1010 '
b1010 )
b1010 -
b10000000000 ,
b10000000000 #
b10000000000 %
b1010 $
#11000
b1011 "
b1011 &
b1011 '
b1011 )
b1011 -
b100000000000 ,
b100000000000 #
b100000000000 %
b1011 $
#12000
b1100 "
b1100 &
b1100 '
b1100 )
b1100 -
b1000000000000 ,
b1000000000000 #
b1000000000000 %
b1100 $
#13000
b1101 "
b1101 &
b1101 '
b1101 )
b1101 -
b10000000000000 ,
b10000000000000 #
b10000000000000 %
b1101 $
#14000
b1110 "
b1110 &
b1110 '
b1110 )
b1110 -
b100000000000000 ,
b100000000000000 #
b100000000000000 %
b1110 $
#15000
b1111 "
b1111 &
b1111 '
b1111 )
b1111 -
b1000000000000000 ,
b1000000000000000 #
b1000000000000000 %
b1111 $
#16000
b1 *
b1 l
12
b10 (
b10 k
0.
b10000 "
b10000 &
b0 '
b0 )
b0 -
b1 0
b0 ,
b10000000000000000 #
b10000000000000000 %
b10000 $
#17000
b10001 "
b10001 &
b1 '
b10000 )
b1 1
b10 0
b100000000000000000 #
b100000000000000000 %
b10001 $
#18000
b10010 "
b10010 &
b10 '
b100000 )
b10 1
b100 0
b1000000000000000000 #
b1000000000000000000 %
b10010 $
#19000
b10011 "
b10011 &
b11 '
b110000 )
b11 1
b1000 0
b10000000000000000000 #
b10000000000000000000 %
b10011 $
#20000
b10100 "
b10100 &
b100 '
b1000000 )
b100 1
b10000 0
b100000000000000000000 #
b100000000000000000000 %
b10100 $
#21000
b10101 "
b10101 &
b101 '
b1010000 )
b101 1
b100000 0
b1000000000000000000000 #
b1000000000000000000000 %
b10101 $
#22000
b10110 "
b10110 &
b110 '
b1100000 )
b110 1
b1000000 0
b10000000000000000000000 #
b10000000000000000000000 %
b10110 $
#23000
b10111 "
b10111 &
b111 '
b1110000 )
b111 1
b10000000 0
b100000000000000000000000 #
b100000000000000000000000 %
b10111 $
#24000
b11000 "
b11000 &
b1000 '
b10000000 )
b1000 1
b100000000 0
b1000000000000000000000000 #
b1000000000000000000000000 %
b11000 $
#25000
b11001 "
b11001 &
b1001 '
b10010000 )
b1001 1
b1000000000 0
b10000000000000000000000000 #
b10000000000000000000000000 %
b11001 $
#26000
b11010 "
b11010 &
b1010 '
b10100000 )
b1010 1
b10000000000 0
b100000000000000000000000000 #
b100000000000000000000000000 %
b11010 $
#27000
b11011 "
b11011 &
b1011 '
b10110000 )
b1011 1
b100000000000 0
b1000000000000000000000000000 #
b1000000000000000000000000000 %
b11011 $
#28000
b11100 "
b11100 &
b1100 '
b11000000 )
b1100 1
b1000000000000 0
b10000000000000000000000000000 #
b10000000000000000000000000000 %
b11100 $
#29000
b11101 "
b11101 &
b1101 '
b11010000 )
b1101 1
b10000000000000 0
b100000000000000000000000000000 #
b100000000000000000000000000000 %
b11101 $
#30000
b11110 "
b11110 &
b1110 '
b11100000 )
b1110 1
b100000000000000 0
b1000000000000000000000000000000 #
b1000000000000000000000000000000 %
b11110 $
#31000
b11111 "
b11111 &
b1111 '
b11110000 )
b1111 1
b1000000000000000 0
b10000000000000000000000000000000 #
b10000000000000000000000000000000 %
b11111 $
#32000
b10 *
b10 l
16
b100 (
b100 k
02
b100000 "
b100000 &
b0 '
b0 )
b0 1
b1 4
b0 0
b100000000000000000000000000000000 #
b100000000000000000000000000000000 %
b100000 $
#33000
b100001 "
b100001 &
b1 '
b100000000 )
b1 5
b10 4
b1000000000000000000000000000000000 #
b1000000000000000000000000000000000 %
b100001 $
#34000
b100010 "
b100010 &
b10 '
b1000000000 )
b10 5
b100 4
b10000000000000000000000000000000000 #
b10000000000000000000000000000000000 %
b100010 $
#35000
b100011 "
b100011 &
b11 '
b1100000000 )
b11 5
b1000 4
b100000000000000000000000000000000000 #
b100000000000000000000000000000000000 %
b100011 $
#36000
b100100 "
b100100 &
b100 '
b10000000000 )
b100 5
b10000 4
b1000000000000000000000000000000000000 #
b1000000000000000000000000000000000000 %
b100100 $
#37000
b100101 "
b100101 &
b101 '
b10100000000 )
b101 5
b100000 4
b10000000000000000000000000000000000000 #
b10000000000000000000000000000000000000 %
b100101 $
#38000
b100110 "
b100110 &
b110 '
b11000000000 )
b110 5
b1000000 4
b100000000000000000000000000000000000000 #
b100000000000000000000000000000000000000 %
b100110 $
#39000
b100111 "
b100111 &
b111 '
b11100000000 )
b111 5
b10000000 4
b1000000000000000000000000000000000000000 #
b1000000000000000000000000000000000000000 %
b100111 $
#40000
b101000 "
b101000 &
b1000 '
b100000000000 )
b1000 5
b100000000 4
b10000000000000000000000000000000000000000 #
b10000000000000000000000000000000000000000 %
b101000 $
#41000
b101001 "
b101001 &
b1001 '
b100100000000 )
b1001 5
b1000000000 4
b100000000000000000000000000000000000000000 #
b100000000000000000000000000000000000000000 %
b101001 $
#42000
b101010 "
b101010 &
b1010 '
b101000000000 )
b1010 5
b10000000000 4
b1000000000000000000000000000000000000000000 #
b1000000000000000000000000000000000000000000 %
b101010 $
#43000
b101011 "
b101011 &
b1011 '
b101100000000 )
b1011 5
b100000000000 4
b10000000000000000000000000000000000000000000 #
b10000000000000000000000000000000000000000000 %
b101011 $
#44000
b101100 "
b101100 &
b1100 '
b110000000000 )
b1100 5
b1000000000000 4
b100000000000000000000000000000000000000000000 #
b100000000000000000000000000000000000000000000 %
b101100 $
#45000
b101101 "
b101101 &
b1101 '
b110100000000 )
b1101 5
b10000000000000 4
b1000000000000000000000000000000000000000000000 #
b1000000000000000000000000000000000000000000000 %
b101101 $
#46000
b101110 "
b101110 &
b1110 '
b111000000000 )
b1110 5
b100000000000000 4
b10000000000000000000000000000000000000000000000 #
b10000000000000000000000000000000000000000000000 %
b101110 $
#47000
b101111 "
b101111 &
b1111 '
b111100000000 )
b1111 5
b1000000000000000 4
b100000000000000000000000000000000000000000000000 #
b100000000000000000000000000000000000000000000000 %
b101111 $
#48000
b11 *
b11 l
1:
b1000 (
b1000 k
06
b110000 "
b110000 &
b0 '
b0 )
b0 5
b1 8
b0 4
b1000000000000000000000000000000000000000000000000 #
b1000000000000000000000000000000000000000000000000 %
b110000 $
#49000
b110001 "
b110001 &
b1 '
b1000000000000 )
b1 9
b10 8
b10000000000000000000000000000000000000000000000000 #
b10000000000000000000000000000000000000000000000000 %
b110001 $
#50000
b110010 "
b110010 &
b10 '
b10000000000000 )
b10 9
b100 8
b100000000000000000000000000000000000000000000000000 #
b100000000000000000000000000000000000000000000000000 %
b110010 $
#51000
b110011 "
b110011 &
b11 '
b11000000000000 )
b11 9
b1000 8
b1000000000000000000000000000000000000000000000000000 #
b1000000000000000000000000000000000000000000000000000 %
b110011 $
#52000
b110100 "
b110100 &
b100 '
b100000000000000 )
b100 9
b10000 8
b10000000000000000000000000000000000000000000000000000 #
b10000000000000000000000000000000000000000000000000000 %
b110100 $
#53000
b110101 "
b110101 &
b101 '
b101000000000000 )
b101 9
b100000 8
b100000000000000000000000000000000000000000000000000000 #
b100000000000000000000000000000000000000000000000000000 %
b110101 $
#54000
b110110 "
b110110 &
b110 '
b110000000000000 )
b110 9
b1000000 8
b1000000000000000000000000000000000000000000000000000000 #
b1000000000000000000000000000000000000000000000000000000 %
b110110 $
#55000
b110111 "
b110111 &
b111 '
b111000000000000 )
b111 9
b10000000 8
b10000000000000000000000000000000000000000000000000000000 #
b10000000000000000000000000000000000000000000000000000000 %
b110111 $
#56000
b111000 "
b111000 &
b1000 '
b1000000000000000 )
b1000 9
b100000000 8
b100000000000000000000000000000000000000000000000000000000 #
b100000000000000000000000000000000000000000000000000000000 %
b111000 $
#57000
b111001 "
b111001 &
b1001 '
b1001000000000000 )
b1001 9
b1000000000 8
b1000000000000000000000000000000000000000000000000000000000 #
b1000000000000000000000000000000000000000000000000000000000 %
b111001 $
#58000
b111010 "
b111010 &
b1010 '
b1010000000000000 )
b1010 9
b10000000000 8
b10000000000000000000000000000000000000000000000000000000000 #
b10000000000000000000000000000000000000000000000000000000000 %
b111010 $
#59000
b111011 "
b111011 &
b1011 '
b1011000000000000 )
b1011 9
b100000000000 8
b100000000000000000000000000000000000000000000000000000000000 #
b100000000000000000000000000000000000000000000000000000000000 %
b111011 $
#60000
b111100 "
b111100 &
b1100 '
b1100000000000000 )
b1100 9
b1000000000000 8
b1000000000000000000000000000000000000000000000000000000000000 #
b1000000000000000000000000000000000000000000000000000000000000 %
b111100 $
#61000
b111101 "
b111101 &
b1101 '
b1101000000000000 )
b1101 9
b10000000000000 8
b10000000000000000000000000000000000000000000000000000000000000 #
b10000000000000000000000000000000000000000000000000000000000000 %
b111101 $
#62000
b111110 "
b111110 &
b1110 '
b1110000000000000 )
b1110 9
b100000000000000 8
b100000000000000000000000000000000000000000000000000000000000000 #
b100000000000000000000000000000000000000000000000000000000000000 %
b111110 $
#63000
b111111 "
b111111 &
b1111 '
b1111000000000000 )
b1111 9
b1000000000000000 8
b1000000000000000000000000000000000000000000000000000000000000000 #
b1000000000000000000000000000000000000000000000000000000000000000 %
b111111 $
#64000
b100 *
b100 l
1>
b10000 (
b10000 k
0:
b1000000 "
b1000000 &
b0 '
b0 )
b0 9
b1 <
b0 8
b10000000000000000000000000000000000000000000000000000000000000000 #
b10000000000000000000000000000000000000000000000000000000000000000 %
b1000000 $
#65000
b1000001 "
b1000001 &
b1 '
b10000000000000000 )
b1 =
b10 <
b100000000000000000000000000000000000000000000000000000000000000000 #
b100000000000000000000000000000000000000000000000000000000000000000 %
b1000001 $
#66000
b1000010 "
b1000010 &
b10 '
b100000000000000000 )
b10 =
b100 <
b1000000000000000000000000000000000000000000000000000000000000000000 #
b1000000000000000000000000000000000000000000000000000000000000000000 %
b1000010 $
#67000
b1000011 "
b1000011 &
b11 '
b110000000000000000 )
b11 =
b1000 <
b10000000000000000000000000000000000000000000000000000000000000000000 #
b10000000000000000000000000000000000000000000000000000000000000000000 %
b1000011 $
#68000
b1000100 "
b1000100 &
b100 '
b1000000000000000000 )
b100 =
b10000 <
b100000000000000000000000000000000000000000000000000000000000000000000 #
b100000000000000000000000000000000000000000000000000000000000000000000 %
b1000100 $
#69000
b1000101 "
b1000101 &
b101 '
b1010000000000000000 )
b101 =
b100000 <
b1000000000000000000000000000000000000000000000000000000000000000000000 #
b1000000000000000000000000000000000000000000000000000000000000000000000 %
b1000101 $
#70000
b1000110 "
b1000110 &
b110 '
b1100000000000000000 )
b110 =
b1000000 <
b10000000000000000000000000000000000000000000000000000000000000000000000 #
b10000000000000000000000000000000000000000000000000000000000000000000000 %
b1000110 $
#71000
b1000111 "
b1000111 &
b111 '
b1110000000000000000 )
b111 =
b10000000 <
b100000000000000000000000000000000000000000000000000000000000000000000000 #
b100000000000000000000000000000000000000000000000000000000000000000000000 %
b1000111 $
#72000
b1001000 "
b1001000 &
b1000 '
b10000000000000000000 )
b1000 =
b100000000 <
b1000000000000000000000000000000000000000000000000000000000000000000000000 #
b1000000000000000000000000000000000000000000000000000000000000000000000000 %
b1001000 $
#73000
b1001001 "
b1001001 &
b1001 '
b10010000000000000000 )
b1001 =
b1000000000 <
b10000000000000000000000000000000000000000000000000000000000000000000000000 #
b10000000000000000000000000000000000000000000000000000000000000000000000000 %
b1001001 $
#74000
b1001010 "
b1001010 &
b1010 '
b10100000000000000000 )
b1010 =
b10000000000 <
b100000000000000000000000000000000000000000000000000000000000000000000000000 #
b100000000000000000000000000000000000000000000000000000000000000000000000000 %
b1001010 $
#75000
b1001011 "
b1001011 &
b1011 '
b10110000000000000000 )
b1011 =
b100000000000 <
b1000000000000000000000000000000000000000000000000000000000000000000000000000 #
b1000000000000000000000000000000000000000000000000000000000000000000000000000 %
b1001011 $
#76000
b1001100 "
b1001100 &
b1100 '
b11000000000000000000 )
b1100 =
b1000000000000 <
b10000000000000000000000000000000000000000000000000000000000000000000000000000 #
b10000000000000000000000000000000000000000000000000000000000000000000000000000 %
b1001100 $
#77000
b1001101 "
b1001101 &
b1101 '
b11010000000000000000 )
b1101 =
b10000000000000 <
b100000000000000000000000000000000000000000000000000000000000000000000000000000 #
b100000000000000000000000000000000000000000000000000000000000000000000000000000 %
b1001101 $
#78000
b1001110 "
b1001110 &
b1110 '
b11100000000000000000 )
b1110 =
b100000000000000 <
b1000000000000000000000000000000000000000000000000000000000000000000000000000000 #
b1000000000000000000000000000000000000000000000000000000000000000000000000000000 %
b1001110 $
#79000
b1001111 "
b1001111 &
b1111 '
b11110000000000000000 )
b1111 =
b1000000000000000 <
b10000000000000000000000000000000000000000000000000000000000000000000000000000000 #
b10000000000000000000000000000000000000000000000000000000000000000000000000000000 %
b1001111 $
#80000
b101 *
b101 l
1B
b100000 (
b100000 k
0>
b1010000 "
b1010000 &
b0 '
b0 )
b0 =
b1 @
b0 <
b100000000000000000000000000000000000000000000000000000000000000000000000000000000 #
b100000000000000000000000000000000000000000000000000000000000000000000000000000000 %
b1010000 $
#81000
b1010001 "
b1010001 &
b1 '
b100000000000000000000 )
b1 A
b10 @
b1000000000000000000000000000000000000000000000000000000000000000000000000000000000 #
b1000000000000000000000000000000000000000000000000000000000000000000000000000000000 %
b1010001 $
#82000
b1010010 "
b1010010 &
b10 '
b1000000000000000000000 )
b10 A
b100 @
b10000000000000000000000000000000000000000000000000000000000000000000000000000000000 #
b10000000000000000000000000000000000000000000000000000000000000000000000000000000000 %
b1010010 $
#83000
b1010011 "
b1010011 &
b11 '
b1100000000000000000000 )
b11 A
b1000 @
b100000000000000000000000000000000000000000000000000000000000000000000000000000000000 #
b100000000000000000000000000000000000000000000000000000000000000000000000000000000000 %
b1010011 $
#84000
b1010100 "
b1010100 &
b100 '
b10000000000000000000000 )
b100 A
b10000 @
b1000000000000000000000000000000000000000000000000000000000000000000000000000000000000 #
b1000000000000000000000000000000000000000000000000000000000000000000000000000000000000 %
b1010100 $
#85000
b1010101 "
b1010101 &
b101 '
b10100000000000000000000 )
b101 A
b100000 @
b10000000000000000000000000000000000000000000000000000000000000000000000000000000000000 #
b10000000000000000000000000000000000000000000000000000000000000000000000000000000000000 %
b1010101 $
#86000
b1010110 "
b1010110 &
b110 '
b11000000000000000000000 )
b110 A
b1000000 @
b100000000000000000000000000000000000000000000000000000000000000000000000000000000000000 #
b100000000000000000000000000000000000000000000000000000000000000000000000000000000000000 %
b1010110 $
#87000
b1010111 "
b1010111 &
b111 '
b11100000000000000000000 )
b111 A
b10000000 @
b1000000000000000000000000000000000000000000000000000000000000000000000000000000000000000 #
b1000000000000000000000000000000000000000000000000000000000000000000000000000000000000000 %
b1010111 $
#88000
b1011000 "
b1011000 &
b1000 '
b100000000000000000000000 )
b1000 A
b100000000 @
b10000000000000000000000000000000000000000000000000000000000000000000000000000000000000000 #
b10000000000000000000000000000000000000000000000000000000000000000000000000000000000000000 %
b1011000 $
#89000
b1011001 "
b1011001 &
b1001 '
b100100000000000000000000 )
b1001 A
b1000000000 @
b100000000000000000000000000000000000000000000000000000000000000000000000000000000000000000 #
b100000000000000000000000000000000000000000000000000000000000000000000000000000000000000000 %
b1011001 $
#90000
b1011010 "
b1011010 &
b1010 '
b101000000000000000000000 )
b1010 A
b10000000000 @
b1000000000000000000000000000000000000000000000000000000000000000000000000000000000000000000 #
b1000000000000000000000000000000000000000000000000000000000000000000000000000000000000000000 %
b1011010 $
#91000
b1011011 "
b1011011 &
b1011 '
b101100000000000000000000 )
b1011 A
b100000000000 @
b10000000000000000000000000000000000000000000000000000000000000000000000000000000000000000000 #
b10000000000000000000000000000000000000000000000000000000000000000000000000000000000000000000 %
b1011011 $
#92000
b1011100 "
b1011100 &
b1100 '
b110000000000000000000000 )
b1100 A
b1000000000000 @
b100000000000000000000000000000000000000000000000000000000000000000000000000000000000000000000 #
b100000000000000000000000000000000000000000000000000000000000000000000000000000000000000000000 %
b1011100 $
#93000
b1011101 "
b1011101 &
b1101 '
b110100000000000000000000 )
b1101 A
b10000000000000 @
b1000000000000000000000000000000000000000000000000000000000000000000000000000000000000000000000 #
b1000000000000000000000000000000000000000000000000000000000000000000000000000000000000000000000 %
b1011101 $
#94000
b1011110 "
b1011110 &
b1110 '
b111000000000000000000000 )
b1110 A
b100000000000000 @
b10000000000000000000000000000000000000000000000000000000000000000000000000000000000000000000000 #
b10000000000000000000000000000000000000000000000000000000000000000000000000000000000000000000000 %
b1011110 $
#95000
b1011111 "
b1011111 &
b1111 '
b111100000000000000000000 )
b1111 A
b1000000000000000 @
b100000000000000000000000000000000000000000000000000000000000000000000000000000000000000000000000 #
b100000000000000000000000000000000000000000000000000000000000000000000000000000000000000000000000 %
b1011111 $
#96000
b110 *
b110 l
1F
b1000000 (
b1000000 k
0B
b1100000 "
b1100000 &
b0 '
b0 )
b0 A
b1 D
b0 @
b1000000000000000000000000000000000000000000000000000000000000000000000000000000000000000000000000 #
b1000000000000000000000000000000000000000000000000000000000000000000000000000000000000000000000000 %
b1100000 $
#97000
b1100001 "
b1100001 &
b1 '
b1000000000000000000000000 )
b1 E
b10 D
b10000000000000000000000000000000000000000000000000000000000000000000000000000000000000000000000000 #
b10000000000000000000000000000000000000000000000000000000000000000000000000000000000000000000000000 %
b1100001 $
#98000
b1100010 "
b1100010 &
b10 '
b10000000000000000000000000 )
b10 E
b100 D
b100000000000000000000000000000000000000000000000000000000000000000000000000000000000000000000000000 #
b100000000000000000000000000000000000000000000000000000000000000000000000000000000000000000000000000 %
b1100010 $
#99000
b1100011 "
b1100011 &
b11 '
b11000000000000000000000000 )
b11 E
b1000 D
b1000000000000000000000000000000000000000000000000000000000000000000000000000000000000000000000000000 #
b1000000000000000000000000000000000000000000000000000000000000000000000000000000000000000000000000000 %
b1100011 $
#100000
b1100100 "
b1100100 &
b100 '
b100000000000000000000000000 )
b100 E
b10000 D
b10000000000000000000000000000000000000000000000000000000000000000000000000000000000000000000000000000 #
b10000000000000000000000000000000000000000000000000000000000000000000000000000000000000000000000000000 %
b1100100 $
#101000
b1100101 "
b1100101 &
b101 '
b101000000000000000000000000 )
b101 E
b100000 D
b100000000000000000000000000000000000000000000000000000000000000000000000000000000000000000000000000000 #
b100000000000000000000000000000000000000000000000000000000000000000000000000000000000000000000000000000 %
b1100101 $
#102000
b1100110 "
b1100110 &
b110 '
b110000000000000000000000000 )
b110 E
b1000000 D
b1000000000000000000000000000000000000000000000000000000000000000000000000000000000000000000000000000000 #
b1000000000000000000000000000000000000000000000000000000000000000000000000000000000000000000000000000000 %
b1100110 $
#103000
b1100111 "
b1100111 &
b111 '
b111000000000000000000000000 )
b111 E
b10000000 D
b10000000000000000000000000000000000000000000000000000000000000000000000000000000000000000000000000000000 #
b10000000000000000000000000000000000000000000000000000000000000000000000000000000000000000000000000000000 %
b1100111 $
#104000
b1101000 "
b1101000 &
b1000 '
b1000000000000000000000000000 )
b1000 E
b100000000 D
b100000000000000000000000000000000000000000000000000000000000000000000000000000000000000000000000000000000 #
b100000000000000000000000000000000000000000000000000000000000000000000000000000000000000000000000000000000 %
b1101000 $
#105000
b1101001 "
b1101001 &
b1001 '
b1001000000000000000000000000 )
b1001 E
b1000000000 D
b1000000000000000000000000000000000000000000000000000000000000000000000000000000000000000000000000000000000 #
b1000000000000000000000000000000000000000000000000000000000000000000000000000000000000000000000000000000000 %
b1101001 $
#106000
b1101010 "
b1101010 &
b1010 '
b1010000000000000000000000000 )
b1010 E
b10000000000 D
b10000000000000000000000000000000000000000000000000000000000000000000000000000000000000000000000000000000000 #
b10000000000000000000000000000000000000000000000000000000000000000000000000000000000000000000000000000000000 %
b1101010 $
#107000
b1101011 "
b1101011 &
b1011 '
b1011000000000000000000000000 )
b1011 E
b100000000000 D
b100000000000000000000000000000000000000000000000000000000000000000000000000000000000000000000000000000000000 #
b100000000000000000000000000000000000000000000000000000000000000000000000000000000000000000000000000000000000 %
b1101011 $
#108000
b1101100 "
b1101100 &
b1100 '
b1100000000000000000000000000 )
b1100 E
b1000000000000 D
b1000000000000000000000000000000000000000000000000000000000000000000000000000000000000000000000000000000000000 #
b1000000000000000000000000000000000000000000000000000000000000000000000000000000000000000000000000000000000000 %
b1101100 $
#109000
b1101101 "
b1101101 &
b1101 '
b1101000000000000000000000000 )
b1101 E
b10000000000000 D
b10000000000000000000000000000000000000000000000000000000000000000000000000000000000000000000000000000000000000 #
b10000000000000000000000000000000000000000000000000000000000000000000000000000000000000000000000000000000000000 %
b1101101 $
#110000
b1101110 "
b1101110 &
b1110 '
b1110000000000000000000000000 )
b1110 E
b100000000000000 D
b100000000000000000000000000000000000000000000000000000000000000000000000000000000000000000000000000000000000000 #
b100000000000000000000000000000000000000000000000000000000000000000000000000000000000000000000000000000000000000 %
b1101110 $
#111000
b1101111 "
b1101111 &
b1111 '
b1111000000000000000000000000 )
b1111 E
b1000000000000000 D
b1000000000000000000000000000000000000000000000000000000000000000000000000000000000000000000000000000000000000000 #
b1000000000000000000000000000000000000000000000000000000000000000000000000000000000000000000000000000000000000000 %
b1101111 $
